{
  "id": "551f8950-43c0-403d-9b87-6d246ded8715",
  "name": "Christopher",
  "heightCm": 142,
  "weightKg": 133,
  "eyeColor": "Blue",
  "hairColor": "White",
  "breed": "Suri",
  "placeOfBirth": "Port Gracechester, Myanmar",
  "description": "Christopher is a blue-eyed llama with white hair, standing 142 cm tall. Originally from Port Gracechester, Myanmar, Christopher enjoys dancing, singing, hiking. Known for their mischievous and curious personality, Christopher is a beloved member of the llama community."
}