{
  "id": "8fed3450-3400-44f1-ae91-2a0e783e8262",
  "name": "Alexa",
  "heightCm": 139,
  "weightKg": 186,
  "eyeColor": "Blue",
  "hairColor": "Gray",
  "breed": "Hybrid",
  "placeOfBirth": "West Philip, Falkland Islands (Malvinas)",
  "description": "Alexa is a blue-eyed llama with gray hair, standing 139 cm tall. Originally from West Philip, Falkland Islands (Malvinas), Alexa enjoys knitting, painting, cooking. Known for their mischievous and curious personality, Alexa is a beloved member of the llama community."
}