{
  "id": "a7361e19-f7f3-4cc7-9af6-baf748949c93",
  "name": "Cody",
  "heightCm": 162,
  "weightKg": 156,
  "eyeColor": "Gray",
  "hairColor": "Gray",
  "breed": "Huacaya",
  "placeOfBirth": "Waltersmouth, Holy See (Vatican City State)",
  "description": "Cody is a gray-eyed llama with gray hair, standing 162 cm tall. Originally from Waltersmouth, Holy See (Vatican City State), Cody enjoys gardening, knitting, dancing. Known for their curious and mischievous personality, Cody is a beloved member of the llama community."
}