{
  "envelope": {
    "headers": {
      "type": "pets"
    },
    "instance": {
      "pets": {
        "id": "76270662-7c0f-4db0-9673-ab562f3500cc",
        "name": "Dimple",
        "ageYears": 1,
        "disposition": "mischievous",
        "fluffiness": 3,
        "quirk": "stages elaborate fake emergencies to see who responds fastest",
        "speciesId": "76cabc17-bbcf-5e4c-a1c7-2fd34d0442ef",
        "speciesCommonName": "Hoatzin",
        "speciesScientificName": "Opisthocomus hoazin",
        "sizeClass": "medium",
        "ownerName": "Clara",
        "shelterId": "869456e1-451e-554f-96f2-4a54e832dd46",
        "shelterName": "Bradley's Extreme Fauna Compound",
        "speciesOntologyIri": "http://cleverllamas.llamaverse/ontology/species#76cabc17-bbcf-5e4c-a1c7-2fd34d0442ef"
      }
    }
  }
}
