{
  "envelope": {
    "headers": {
      "type": "pets"
    },
    "instance": {
      "pets": {
        "id": "9bb37076-8067-4fcd-b16c-05539a5cdd91",
        "name": "Snapper",
        "ageYears": 0,
        "disposition": "earnest",
        "fluffiness": 1,
        "quirk": "stages elaborate fake emergencies to see who responds fastest",
        "speciesId": "ae2e8ce1-dd67-555a-93b2-1d567d30adb4",
        "speciesCommonName": "Tardigrade \u2014 Water Bear (Arctic)",
        "speciesScientificName": "Milnesium tardigradum",
        "sizeClass": "microscopic",
        "ownerName": "Isolde",
        "shelterId": "c8de3d2b-6e9a-5ed1-bda7-9a50f977ddb9",
        "shelterName": "The Quiet Pool"
      }
    }
  }
}