{
  "envelope": {
    "headers": {
      "type": "pets"
    },
    "instance": {
      "pets": {
        "id": "ae36ac05-8a82-44b0-a1e9-33fdff00c209",
        "name": "Swoopington",
        "ageYears": 0,
        "disposition": "theatrical",
        "fluffiness": 1,
        "quirk": "sings exactly one note whenever startled",
        "speciesId": "acbe160a-34a5-5c3e-b09b-16f95ee4ebeb",
        "speciesCommonName": "Mimic Octopus",
        "speciesScientificName": "Thaumoctopus mimicus",
        "sizeClass": "small",
        "ownerName": "Freddie",
        "shelterId": "a80124a7-0a88-582c-9362-e5c7aecd90d2",
        "shelterName": "The Peculiar Menagerie of Llamaville East",
        "speciesOntologyIri": "http://cleverllamas.llamaverse/ontology/species#acbe160a-34a5-5c3e-b09b-16f95ee4ebeb"
      }
    }
  }
}
